contracts_lib_py/__init__.py
contracts_lib_py/account.py
contracts_lib_py/contract_base.py
contracts_lib_py/contract_handler.py
contracts_lib_py/diagnostics.py
contracts_lib_py/didregistry.py
contracts_lib_py/dispenser.py
contracts_lib_py/event_filter.py
contracts_lib_py/event_listener.py
contracts_lib_py/exceptions.py
contracts_lib_py/generic_contract.py
contracts_lib_py/keeper.py
contracts_lib_py/nft721_upgradeable.py
contracts_lib_py/nft_upgradeable.py
contracts_lib_py/token.py
contracts_lib_py/utils.py
contracts_lib_py/wallet.py
contracts_lib_py/web3_provider.py
contracts_lib_py/agreements/__init__.py
contracts_lib_py/agreements/agreement_manager.py
contracts_lib_py/conditions/__init__.py
contracts_lib_py/conditions/access.py
contracts_lib_py/conditions/access_proof.py
contracts_lib_py/conditions/compute_execution.py
contracts_lib_py/conditions/condition_base.py
contracts_lib_py/conditions/condition_manager.py
contracts_lib_py/conditions/escrow_reward.py
contracts_lib_py/conditions/hash_lock.py
contracts_lib_py/conditions/lock_reward.py
contracts_lib_py/conditions/nft721_escrow_reward.py
contracts_lib_py/conditions/nft_access.py
contracts_lib_py/conditions/nft_escrow_reward.py
contracts_lib_py/conditions/nft_holder.py
contracts_lib_py/conditions/nft_lock_condition.py
contracts_lib_py/conditions/sign.py
contracts_lib_py/conditions/threshold.py
contracts_lib_py/conditions/transfer_did.py
contracts_lib_py/conditions/transfer_nft.py
contracts_lib_py/conditions/transfer_nft721.py
contracts_lib_py/conditions/white_listing.py
contracts_lib_py/templates/__init__.py
contracts_lib_py/templates/access_proof_template.py
contracts_lib_py/templates/access_template.py
contracts_lib_py/templates/compute_execution_template.py
contracts_lib_py/templates/did_sales_template.py
contracts_lib_py/templates/nft721_sales_template.py
contracts_lib_py/templates/nft_access_proof_template.py
contracts_lib_py/templates/nft_access_swap_template.py
contracts_lib_py-1.0.4.dist-info/LICENSE
contracts_lib_py-1.0.4.dist-info/METADATA
contracts_lib_py-1.0.4.dist-info/NOTICE
contracts_lib_py-1.0.4.dist-info/WHEEL
contracts_lib_py-1.0.4.dist-info/top_level.txt
contracts_lib_py-1.0.4.dist-info/RECORD
