Metadata-Version: 2.1
Name: contracts-lib-py
Version: 1.0.4
Summary: 🐳 Library including all the common functionalities used in Python projects
Home-page: https://github.com/nevermined-io/contracts-lib-py
Author: nevermined-io
Author-email: root@nevermined.io
License: Apache Software License 2.0
Keywords: contracts-lib-py
Platform: UNKNOWN
Classifier: Development Status :: 5 - Production/Stable
Classifier: Intended Audience :: Developers
Classifier: License :: OSI Approved :: Apache Software License
Classifier: Natural Language :: English
Classifier: Programming Language :: Python :: 3.7
Classifier: Programming Language :: Python :: 3.8
License-File: LICENSE
License-File: NOTICE
Requires-Dist: nevermined-contracts (==2.0.3)
Requires-Dist: web3 (==5.26.0)
Requires-Dist: requests (==2.21.0)
Provides-Extra: dev
Requires-Dist: bumpversion ; extra == 'dev'
Requires-Dist: pkginfo ; extra == 'dev'
Requires-Dist: twine ; extra == 'dev'
Requires-Dist: watchdog ; extra == 'dev'
Requires-Dist: codacy-coverage ; extra == 'dev'
Requires-Dist: coverage ; extra == 'dev'
Requires-Dist: docker ; extra == 'dev'
Requires-Dist: mccabe ; extra == 'dev'
Requires-Dist: pylint ; extra == 'dev'
Requires-Dist: pytest ; extra == 'dev'
Requires-Dist: pytest-watch ; extra == 'dev'
Requires-Dist: Sphinx ; extra == 'dev'
Requires-Dist: sphinxcontrib-apidoc ; extra == 'dev'
Provides-Extra: docs
Requires-Dist: Sphinx ; extra == 'docs'
Requires-Dist: sphinxcontrib-apidoc ; extra == 'docs'
Provides-Extra: test
Requires-Dist: codacy-coverage ; extra == 'test'
Requires-Dist: coverage ; extra == 'test'
Requires-Dist: docker ; extra == 'test'
Requires-Dist: mccabe ; extra == 'test'
Requires-Dist: pylint ; extra == 'test'
Requires-Dist: pytest ; extra == 'test'
Requires-Dist: pytest-watch ; extra == 'test'
